parsim/__init__.py
parsim/cli.py
parsim/commands.py
parsim/core.py
parsim/dakota.py
parsim/doe.py
parsim/expander.py
parsim/loggers.py
parsim-2.2.0.dist-info/licenses/LICENSE
parsim-2.2.0.dist-info/METADATA
parsim-2.2.0.dist-info/WHEEL
parsim-2.2.0.dist-info/entry_points.txt
parsim-2.2.0.dist-info/top_level.txt
parsim-2.2.0.dist-info/RECORD
