Metadata-Version: 2.4
Name: parsim
Version: 2.2.0
Summary: A tool for working with parameterized simulation models
Author-email: Ola Widlund <ola.widlund@ri.se>
License-Expression: GPL-3.0-only
Project-URL: Homepage, https://gitlab.com/olwi/psm
Project-URL: Documentation, https://parsim.readthedocs.io/en/latest/index.html
Project-URL: Repository, https://gitlab.com/olwi/psm.git
Project-URL: Issues, https://gitlab.com/olwi/psm/-/issues
Project-URL: Changelog, https://gitlab.com/olwi/psm/-/blob/master/CHANGELOG.rst
Keywords: simulation,numerical modeling,doe,design of experiments,sampling,dakota,vvuq,quality assurance,qa,uq,uncertainty quantification,parameterization,parameterized models
Classifier: Development Status :: 5 - Production/Stable
Classifier: Intended Audience :: Developers
Classifier: Intended Audience :: Science/Research
Classifier: Intended Audience :: Manufacturing
Classifier: Topic :: Scientific/Engineering
Classifier: Programming Language :: Python :: 3
Classifier: Operating System :: OS Independent
Classifier: Environment :: Console
Requires-Python: >=3.8
License-File: LICENSE
Requires-Dist: pyexpander>=1.9
Requires-Dist: numpy
Requires-Dist: scipy
Requires-Dist: pyDOE3
Requires-Dist: pandas
Dynamic: license-file
